pyquaternion/__init__.py
pyquaternion/quaternion.py
pyquaternion-0.9.8.dist-info/LICENSE.txt
pyquaternion-0.9.8.dist-info/METADATA
pyquaternion-0.9.8.dist-info/WHEEL
pyquaternion-0.9.8.dist-info/top_level.txt
pyquaternion-0.9.8.dist-info/RECORD
